chesspuzzlekit/__init__.py
chesspuzzlekit/_db.py
chesspuzzlekit/puzzles.py
chesspuzzlekit-1.3.0.dist-info/licenses/LICENSE
tests/__init__.py
tests/conftest.py
tests/test_puzzles.py
chesspuzzlekit-1.3.0.dist-info/METADATA
chesspuzzlekit-1.3.0.dist-info/WHEEL
chesspuzzlekit-1.3.0.dist-info/top_level.txt
chesspuzzlekit-1.3.0.dist-info/RECORD
