Metadata-Version: 2.4
Name: ChessPuzzleKit
Version: 1.3.0
Summary: A Python library for retrieving and filtering chess puzzles from the Lichess database.
Author-email: Jack Scallan <breezechess99@gmail.com>
License: MIT
Project-URL: Homepage, https://github.com/JackScallan02/chess-puzzle-kit
Project-URL: Repository, https://github.com/JackScallan02/chess-puzzle-kit
Requires-Python: >=3.7
License-File: LICENSE
Requires-Dist: requests
Requires-Dist: pandas
Requires-Dist: psycopg2
Provides-Extra: dev
Requires-Dist: pytest; extra == "dev"
Requires-Dist: black; extra == "dev"
Requires-Dist: ruff; extra == "dev"
Dynamic: license-file
